park_nyc-0.0.1.dev0.dist-info/DESCRIPTION.rst
park_nyc-0.0.1.dev0.dist-info/LICENSE.txt
park_nyc-0.0.1.dev0.dist-info/METADATA
park_nyc-0.0.1.dev0.dist-info/RECORD
park_nyc-0.0.1.dev0.dist-info/WHEEL
park_nyc-0.0.1.dev0.dist-info/metadata.json
park_nyc-0.0.1.dev0.dist-info/top_level.txt
parknyc/__init__.py
parknyc/exceptions.py
parknyc/service.py
