Metadata-Version: 2.0
Name: park-nyc
Version: 0.0.1.dev0
Summary: Unofficial ParkNYC API Python wrapper
Home-page: https://github.com/alecxe/park-nyc
Author: Alexander Afanasyev
Author-email: me@alecxe.me
License: MIT
Keywords: api parking nyc
Platform: UNKNOWN
Classifier: Development Status :: 3 - Alpha
Classifier: Intended Audience :: Developers
Classifier: License :: OSI Approved :: MIT License
Classifier: Programming Language :: Python
Classifier: Programming Language :: Python :: 2
Classifier: Programming Language :: Python :: 2.6
Classifier: Programming Language :: Python :: 2.7
Classifier: Programming Language :: Python :: 3
Classifier: Programming Language :: Python :: 3.3
Classifier: Programming Language :: Python :: 3.4
Classifier: Programming Language :: Python :: 3.5
Classifier: Programming Language :: Python :: 3.6
Classifier: Topic :: Software Development :: Libraries
Classifier: Topic :: Internet :: WWW/HTTP
Requires-Dist: requests
